wmi_client_wrapper
