Metadata-Version: 1.1
Name: wmi-client-wrapper
Version: 0.0.6
Summary: Linux-only wrapper around wmi-client for WMI (Windows)
Home-page: https://github.com/kanzure/python-wmi-client-wrapper
Author: Bryan Bishop
Author-email: kanzure@gmail.com
License: BSD
Platform: any
Classifier: License :: OSI Approved :: BSD License
Classifier: Topic :: Software Development :: Libraries :: Python Modules
Classifier: Programming Language :: Python
Classifier: Programming Language :: Python :: 2.7
